{
    "updated_at": "2025-08-31T12:22:26.119346+00:00",
    "news": [
        {
            "title": "China and India pledge to be 'partners not rivals'",
            "link": "https://www.bbc.com/news/articles/clyrwv0egzro?at_medium=RSS&at_campaign=rss",
            "published": "Sun, 31 Aug 2025 09:14:19 GMT",
            "source": "BBC"
        },
        {
            "title": "Reeling from Trump's tariffs, India and China seek a business reboot",
            "link": "https://www.bbc.com/news/articles/c0mlen3grx7o?at_medium=RSS&at_campaign=rss",
            "published": "Sun, 31 Aug 2025 05:02:48 GMT",
            "source": "BBC"
        },
        {
            "title": "Thousands attend Australia anti-immigration rallies",
            "link": "https://www.bbc.com/news/articles/czjmre371l1o?at_medium=RSS&at_campaign=rss",
            "published": "Sun, 31 Aug 2025 09:29:39 GMT",
            "source": "BBC"
        },
        {
            "title": "Prominent Ukrainian politician Andriy Parubiy shot dead in Lviv",
            "link": "https://www.bbc.com/news/articles/cjw6ep37469o?at_medium=RSS&at_campaign=rss",
            "published": "Sat, 30 Aug 2025 16:41:58 GMT",
            "source": "BBC"
        },
        {
            "title": "Australian state to ban iconic fish-shaped soy sauce containers",
            "link": "https://www.bbc.com/news/articles/c1ejwgq3zw0o?at_medium=RSS&at_campaign=rss",
            "published": "Sun, 31 Aug 2025 11:45:34 GMT",
            "source": "BBC"
        },
        {
            "title": "Barrier being built around besieged Sudan city, satellite images show",
            "link": "https://www.bbc.com/news/articles/c4gz1ekdee3o?at_medium=RSS&at_campaign=rss",
            "published": "Sat, 30 Aug 2025 01:02:45 GMT",
            "source": "BBC"
        },
        {
            "title": "French voice fears over Bayeux Tapestry move to UK",
            "link": "https://www.bbc.com/news/articles/cev23vrzx0ro?at_medium=RSS&at_campaign=rss",
            "published": "Sun, 31 Aug 2025 00:37:28 GMT",
            "source": "BBC"
        },
        {
            "title": "Head-on crash between police van and prison bus kills 14 in Namibia",
            "link": "https://www.bbc.com/news/articles/c3v3g9z139wo?at_medium=RSS&at_campaign=rss",
            "published": "Sun, 31 Aug 2025 10:49:12 GMT",
            "source": "BBC"
        },
        {
            "title": "Houthis confirm their prime minister killed in Israeli strike",
            "link": "https://www.bbc.com/news/articles/c620ykrxedwo?at_medium=RSS&at_campaign=rss",
            "published": "Sat, 30 Aug 2025 20:39:24 GMT",
            "source": "BBC"
        },
        {
            "title": "Thousands demonstrate across Mexico for the 130,000 missing",
            "link": "https://www.bbc.com/news/articles/ckg4rnr720yo?at_medium=RSS&at_campaign=rss",
            "published": "Sun, 31 Aug 2025 03:58:48 GMT",
            "source": "BBC"
        },
        {
            "title": "Trump pleads not guilty to 34 felony counts",
            "link": "https://edition.cnn.com/webview/politics/live-news/trump-indictment-stormy-daniels-news-04-03-23/index.html",
            "published": "N/A",
            "source": "CNN"
        },
        {
            "title": "Haberman reveals why Trump attacked judge and his family in speech",
            "link": "https://www.cnn.com/videos/politics/2023/04/05/maggie-haberman-donald-trump-speech-indictment-reaction-sot-cnntm-vpx.cnn",
            "published": "Wed, 05 Apr 2023 13:30:09 GMT",
            "source": "CNN"
        },
        {
            "title": "What to know about the Trump indictment on the eve of his court appearance",
            "link": "https://www.cnn.com/collections/intl-trump-040223/",
            "published": "Wed, 05 Apr 2023 22:50:06 GMT",
            "source": "CNN"
        },
        {
            "title": "READ: Trump indictment related to hush money payment",
            "link": "https://cnn.it/411KYN7",
            "published": "N/A",
            "source": "CNN"
        },
        {
            "title": "Russian authorities detain suspect over St. Petersburg cafe blast",
            "link": "https://edition.cnn.com/webview/europe/live-news/russia-ukraine-war-news-04-03-23/index.html",
            "published": "N/A",
            "source": "CNN"
        },
        {
            "title": "Video shows moment of deadly explosion at cafe in Russia",
            "link": "https://www.cnn.com/videos/world/2023/04/02/russian-military-blogger-vladlen-tatarsky-killed-cafe-explosion-chance-vpx.cnn",
            "published": "Tue, 04 Apr 2023 01:08:44 GMT",
            "source": "CNN"
        },
        {
            "title": "Wall Street Journal reporter Evan Gershkovich appeals against arrest, Russian state media says",
            "link": "https://www.cnn.com/collections/intl-ukraine-030423/",
            "published": "Mon, 03 Apr 2023 13:58:58 GMT",
            "source": "CNN"
        },
        {
            "title": "Suspected Chinese spy balloon was able to transmit information back to Beijing",
            "link": "https://www.cnn.com/2023/04/03/politics/chinese-spy-balloon/index.html",
            "published": "Mon, 03 Apr 2023 13:38:22 GMT",
            "source": "CNN"
        },
        {
            "title": "Beijing promised to 'fight back' over Taiwan leader's US visit. But this time it has more to lose",
            "link": "https://www.cnn.com/2023/04/04/asia/tsai-ing-wen-taiwan-mccarthy-meeting-analysis-intl-hnk/index.html",
            "published": "Tue, 04 Apr 2023 07:49:53 GMT",
            "source": "CNN"
        },
        {
            "title": "'Scary, cold, hungry and lonely': Volunteer soldier shares experience on front line",
            "link": "https://www.cnn.com/videos/world/2023/04/03/soldiers-russia-ukraine-war-david-mckenzie-pkg-ovn-intl-ldn-vpx.cnn",
            "published": "Mon, 03 Apr 2023 12:13:24 GMT",
            "source": "CNN"
        },
        {
            "title": "SCO summit: Xi, Modi seek closer China-India ties",
            "link": "https://www.dw.com/en/sco-summit-xi-modi-seek-closer-china-india-ties/live-73823604?maca=en-rss-en-top-1022-rdf",
            "published": "2025-08-31T10:51:00Z",
            "source": "DW (Germany)"
        },
        {
            "title": "EuroBasket: Germany's Schröder decries racial abuse",
            "link": "https://www.dw.com/en/eurobasket-germany-s-schröder-decries-racial-abuse/a-73825500?maca=en-rss-en-top-1022-rdf",
            "published": "2025-08-31T10:34:00Z",
            "source": "DW (Germany)"
        },
        {
            "title": "Middle East: Greta Thunberg to embark on Gaza-bound flotilla",
            "link": "https://www.dw.com/en/middle-east-greta-thunberg-to-embark-on-gaza-bound-flotilla/live-73818605?maca=en-rss-en-top-1022-rdf",
            "published": "2025-08-31T09:55:00Z",
            "source": "DW (Germany)"
        },
        {
            "title": "Indonesia: President calls protests 'treason and terrorism'",
            "link": "https://www.dw.com/en/indonesia-president-calls-protests-treason-and-terrorism/a-73825108?maca=en-rss-en-top-1022-rdf",
            "published": "2025-08-31T09:09:00Z",
            "source": "DW (Germany)"
        },
        {
            "title": "Germany updates: Merkel's 'Wir schaffen das!' 10 years on",
            "link": "https://www.dw.com/en/germany-updates-merkel-s-wir-schaffen-das-10-years-on/live-73819015?maca=en-rss-en-top-1022-rdf",
            "published": "2025-08-31T05:55:00Z",
            "source": "DW (Germany)"
        },
        {
            "title": "SCO summit: World leaders gather in China's Tianjin",
            "link": "https://www.dw.com/en/sco-summit-world-leaders-gather-in-china-s-tianjin/a-73823580?maca=en-rss-en-top-1022-rdf",
            "published": "2025-08-31T02:47:00Z",
            "source": "DW (Germany)"
        },
        {
            "title": "Hundreds at Voice of America and parent agency to lose jobs",
            "link": "https://www.dw.com/en/hundreds-at-voice-of-america-and-parent-agency-to-lose-jobs/a-73823031?maca=en-rss-en-top-1022-rdf",
            "published": "2025-08-31T01:06:00Z",
            "source": "DW (Germany)"
        },
        {
            "title": "Germany: Ireland voices concern over Berlin police violence",
            "link": "https://www.dw.com/en/germany-ireland-voices-concern-over-berlin-police-violence/a-73822510?maca=en-rss-en-top-1022-rdf",
            "published": "2025-08-30T21:28:00Z",
            "source": "DW (Germany)"
        },
        {
            "title": "How much screen time is safe for children?",
            "link": "https://www.dw.com/en/how-much-screen-time-is-safe-for-children/a-73822160?maca=en-rss-en-top-1022-rdf",
            "published": "2025-08-30T19:10:00Z",
            "source": "DW (Germany)"
        },
        {
            "title": "'Currydurst': Beer and curry ketchup in a glass",
            "link": "https://www.dw.com/en/currydurst-beer-and-curry-ketchup-in-a-glass/a-73799017?maca=en-rss-en-top-1022-rdf",
            "published": "2025-08-30T17:16:00Z",
            "source": "DW (Germany)"
        }
    ]
}