{
    "updated_at": "2025-06-01T12:23:06.988616+00:00",
    "news": [
        {
            "title": "Two dead and hundreds arrested in France after PSG Champions League win",
            "link": "https://www.bbc.com/news/articles/ckgqyg325gno",
            "published": "Sun, 01 Jun 2025 12:22:22 GMT",
            "source": "BBC"
        },
        {
            "title": "Hamas makes hostage pledge but demands changes to US Gaza ceasefire plan",
            "link": "https://www.bbc.com/news/articles/c17rzyw72jko",
            "published": "Sat, 31 May 2025 21:57:31 GMT",
            "source": "BBC"
        },
        {
            "title": "31 killed in Israeli tank fire near Gaza aid centre, health ministry says",
            "link": "https://www.bbc.com/news/articles/c991j01lym3o",
            "published": "Sun, 01 Jun 2025 12:03:33 GMT",
            "source": "BBC"
        },
        {
            "title": "At least seven dead after two Russian bridges collapse",
            "link": "https://www.bbc.com/news/articles/cr7zjy89304o",
            "published": "Sun, 01 Jun 2025 06:57:35 GMT",
            "source": "BBC"
        },
        {
            "title": "Silent acts of resistance and fear under Russian occupation in Ukraine",
            "link": "https://www.bbc.com/news/articles/czj40rn8k0wo",
            "published": "Sat, 31 May 2025 23:53:22 GMT",
            "source": "BBC"
        },
        {
            "title": "US sends nuclear deal proposal to Iran",
            "link": "https://www.bbc.com/news/articles/ce82g704rd2o",
            "published": "Sun, 01 Jun 2025 01:06:16 GMT",
            "source": "BBC"
        },
        {
            "title": "Military aircraft evacuates residents from fast-moving Canada fire",
            "link": "https://www.bbc.com/news/articles/cz9yv2g07p0o",
            "published": "Sat, 31 May 2025 16:39:06 GMT",
            "source": "BBC"
        },
        {
            "title": "Heartbreak as cash-strapped Nigerians abandon their pets",
            "link": "https://www.bbc.com/news/articles/cy8nkr3yp88o",
            "published": "Sun, 01 Jun 2025 00:18:09 GMT",
            "source": "BBC"
        },
        {
            "title": "EU 'strongly' regrets US plan to double steel tariffs",
            "link": "https://www.bbc.com/news/articles/cx2eg42nzpwo",
            "published": "Sat, 31 May 2025 17:15:34 GMT",
            "source": "BBC"
        },
        {
            "title": "Desperate Housewives star Valerie Mahaffey dies aged 71",
            "link": "https://www.bbc.com/news/articles/cn4q23ge7xjo",
            "published": "Sat, 31 May 2025 14:37:17 GMT",
            "source": "BBC"
        },
        {
            "title": "Trump pleads not guilty to 34 felony counts",
            "link": "https://edition.cnn.com/webview/politics/live-news/trump-indictment-stormy-daniels-news-04-03-23/index.html",
            "published": "N/A",
            "source": "CNN"
        },
        {
            "title": "Haberman reveals why Trump attacked judge and his family in speech",
            "link": "https://www.cnn.com/videos/politics/2023/04/05/maggie-haberman-donald-trump-speech-indictment-reaction-sot-cnntm-vpx.cnn",
            "published": "Wed, 05 Apr 2023 13:30:09 GMT",
            "source": "CNN"
        },
        {
            "title": "What to know about the Trump indictment on the eve of his court appearance",
            "link": "https://www.cnn.com/collections/intl-trump-040223/",
            "published": "Wed, 05 Apr 2023 22:50:06 GMT",
            "source": "CNN"
        },
        {
            "title": "READ: Trump indictment related to hush money payment",
            "link": "https://cnn.it/411KYN7",
            "published": "N/A",
            "source": "CNN"
        },
        {
            "title": "Russian authorities detain suspect over St. Petersburg cafe blast",
            "link": "https://edition.cnn.com/webview/europe/live-news/russia-ukraine-war-news-04-03-23/index.html",
            "published": "N/A",
            "source": "CNN"
        },
        {
            "title": "Video shows moment of deadly explosion at cafe in Russia",
            "link": "https://www.cnn.com/videos/world/2023/04/02/russian-military-blogger-vladlen-tatarsky-killed-cafe-explosion-chance-vpx.cnn",
            "published": "Tue, 04 Apr 2023 01:08:44 GMT",
            "source": "CNN"
        },
        {
            "title": "Wall Street Journal reporter Evan Gershkovich appeals against arrest, Russian state media says",
            "link": "https://www.cnn.com/collections/intl-ukraine-030423/",
            "published": "Mon, 03 Apr 2023 13:58:58 GMT",
            "source": "CNN"
        },
        {
            "title": "Suspected Chinese spy balloon was able to transmit information back to Beijing",
            "link": "https://www.cnn.com/2023/04/03/politics/chinese-spy-balloon/index.html",
            "published": "Mon, 03 Apr 2023 13:38:22 GMT",
            "source": "CNN"
        },
        {
            "title": "Beijing promised to 'fight back' over Taiwan leader's US visit. But this time it has more to lose",
            "link": "https://www.cnn.com/2023/04/04/asia/tsai-ing-wen-taiwan-mccarthy-meeting-analysis-intl-hnk/index.html",
            "published": "Tue, 04 Apr 2023 07:49:53 GMT",
            "source": "CNN"
        },
        {
            "title": "'Scary, cold, hungry and lonely': Volunteer soldier shares experience on front line",
            "link": "https://www.cnn.com/videos/world/2023/04/03/soldiers-russia-ukraine-war-david-mckenzie-pkg-ovn-intl-ldn-vpx.cnn",
            "published": "Mon, 03 Apr 2023 12:13:24 GMT",
            "source": "CNN"
        },
        {
            "title": "Germany updates: Severe storms hit several states",
            "link": "https://www.dw.com/en/germany-updates-severe-storms-hit-several-states/live-72749136?maca=en-rss-en-top-1022-rdf",
            "published": "2025-06-01T11:18:00Z",
            "source": "DW (Germany)"
        },
        {
            "title": "Czech-Slovak relations chill to glacial",
            "link": "https://www.dw.com/en/czech-slovak-relations-chill-to-glacial/a-72697750?maca=en-rss-en-top-1022-rdf",
            "published": "2025-06-01T10:47:00Z",
            "source": "DW (Germany)"
        },
        {
            "title": "Middle East updates: Palestinians killed at Gaza aid site",
            "link": "https://www.dw.com/en/middle-east-updates-palestinians-killed-at-gaza-aid-site/live-72748195?maca=en-rss-en-top-1022-rdf",
            "published": "2025-06-01T09:40:00Z",
            "source": "DW (Germany)"
        },
        {
            "title": "Russia reports collapse of bridges in Bryansk, Kursk",
            "link": "https://www.dw.com/en/russia-reports-collapse-of-bridges-in-bryansk-kursk/a-72746930?maca=en-rss-en-top-1022-rdf",
            "published": "2025-06-01T08:43:00Z",
            "source": "DW (Germany)"
        },
        {
            "title": "Germany: Fire at Hamburg hospital kills 3, injures over 50",
            "link": "https://www.dw.com/en/germany-fire-at-hamburg-hospital-kills-3-injures-over-50/a-72746981?maca=en-rss-en-top-1022-rdf",
            "published": "2025-06-01T08:37:00Z",
            "source": "DW (Germany)"
        },
        {
            "title": "Parenthood in Europe: Less life satisfaction, but more meaning in life",
            "link": "https://www.dw.com/en/parenthood-in-europe-less-life-satisfaction-but-more-meaning-in-life/a-72746429?maca=en-rss-en-top-1022-rdf",
            "published": "2025-06-01T06:21:00Z",
            "source": "DW (Germany)"
        },
        {
            "title": "Turkey sees sharp rise in obesity",
            "link": "https://www.dw.com/en/turkey-sees-sharp-rise-in-obesity/a-72701125?maca=en-rss-en-top-1022-rdf",
            "published": "2025-06-01T05:33:00Z",
            "source": "DW (Germany)"
        },
        {
            "title": "Poland election: Polls open in tight presidential runoff",
            "link": "https://www.dw.com/en/poland-election-polls-open-in-tight-presidential-runoff/live-72747255?maca=en-rss-en-top-1022-rdf",
            "published": "2025-06-01T05:11:00Z",
            "source": "DW (Germany)"
        },
        {
            "title": "PSG and Qatar finally reach Champions League summit",
            "link": "https://www.dw.com/en/psg-and-qatar-finally-reach-champions-league-summit/a-72746785?maca=en-rss-en-top-1022-rdf",
            "published": "2025-05-31T23:27:00Z",
            "source": "DW (Germany)"
        },
        {
            "title": "Paris Saint-Germain set new record beating Inter 5-0 in Champions League final",
            "link": "https://www.dw.com/en/paris-saint-germain-set-new-record-beating-inter-5-0-in-champions-league-final/a-72746572?maca=en-rss-en-top-1022-rdf",
            "published": "2025-05-31T20:50:00Z",
            "source": "DW (Germany)"
        }
    ]
}