{
    "updated_at": "2025-10-02T12:23:50.168243+00:00",
    "news": [
        {
            "title": "Israel intercepts Gaza flotilla and detains activists including Greta Thunberg",
            "link": "https://www.bbc.com/news/articles/c0lk292jww4o?at_medium=RSS&at_campaign=rss",
            "published": "Thu, 02 Oct 2025 12:00:46 GMT",
            "source": "BBC"
        },
        {
            "title": "Hamas military leader in Gaza objects to ceasefire plan, BBC understands",
            "link": "https://www.bbc.com/news/articles/c708v2q5r09o?at_medium=RSS&at_campaign=rss",
            "published": "Thu, 02 Oct 2025 10:54:37 GMT",
            "source": "BBC"
        },
        {
            "title": "White House says layoffs 'imminent' with no end to shutdown in sight",
            "link": "https://www.bbc.com/news/articles/c8xrwdny8p1o?at_medium=RSS&at_campaign=rss",
            "published": "Thu, 02 Oct 2025 10:40:51 GMT",
            "source": "BBC"
        },
        {
            "title": "Four ways this US government shutdown could end",
            "link": "https://www.bbc.com/news/articles/cdr6pnky7vyo?at_medium=RSS&at_campaign=rss",
            "published": "Wed, 01 Oct 2025 18:25:22 GMT",
            "source": "BBC"
        },
        {
            "title": "Attenborough and Prince William lead tributes to Dr Jane Goodall",
            "link": "https://www.bbc.com/news/articles/czrp24myrl7o?at_medium=RSS&at_campaign=rss",
            "published": "Thu, 02 Oct 2025 11:45:13 GMT",
            "source": "BBC"
        },
        {
            "title": "Dozens feared dead in Indonesia school collapse, officials say",
            "link": "https://www.bbc.com/news/articles/c8d783yjvpyo?at_medium=RSS&at_campaign=rss",
            "published": "Thu, 02 Oct 2025 07:04:20 GMT",
            "source": "BBC"
        },
        {
            "title": "Musk becomes world's first half-trillionaire",
            "link": "https://www.bbc.com/news/articles/c89d3547npjo?at_medium=RSS&at_campaign=rss",
            "published": "Thu, 02 Oct 2025 01:45:44 GMT",
            "source": "BBC"
        },
        {
            "title": "First killings in Morocco since Gen Z protests erupted",
            "link": "https://www.bbc.com/news/articles/cgrqpekyxpvo?at_medium=RSS&at_campaign=rss",
            "published": "Thu, 02 Oct 2025 11:31:03 GMT",
            "source": "BBC"
        },
        {
            "title": "'Area of interest' found in search for girl who vanished 55 years ago",
            "link": "https://www.bbc.com/news/articles/cr4qp95n0pzo?at_medium=RSS&at_campaign=rss",
            "published": "Thu, 02 Oct 2025 09:07:14 GMT",
            "source": "BBC"
        },
        {
            "title": "Israel 'tightens siege' of Gaza City as Hamas reviews Trump peace plan",
            "link": "https://www.bbc.com/news/articles/cvgnznkjrx6o?at_medium=RSS&at_campaign=rss",
            "published": "Wed, 01 Oct 2025 16:38:26 GMT",
            "source": "BBC"
        },
        {
            "title": "Trump pleads not guilty to 34 felony counts",
            "link": "https://edition.cnn.com/webview/politics/live-news/trump-indictment-stormy-daniels-news-04-03-23/index.html",
            "published": "N/A",
            "source": "CNN"
        },
        {
            "title": "Haberman reveals why Trump attacked judge and his family in speech",
            "link": "https://www.cnn.com/videos/politics/2023/04/05/maggie-haberman-donald-trump-speech-indictment-reaction-sot-cnntm-vpx.cnn",
            "published": "Wed, 05 Apr 2023 13:30:09 GMT",
            "source": "CNN"
        },
        {
            "title": "What to know about the Trump indictment on the eve of his court appearance",
            "link": "https://www.cnn.com/collections/intl-trump-040223/",
            "published": "Wed, 05 Apr 2023 22:50:06 GMT",
            "source": "CNN"
        },
        {
            "title": "READ: Trump indictment related to hush money payment",
            "link": "https://cnn.it/411KYN7",
            "published": "N/A",
            "source": "CNN"
        },
        {
            "title": "Russian authorities detain suspect over St. Petersburg cafe blast",
            "link": "https://edition.cnn.com/webview/europe/live-news/russia-ukraine-war-news-04-03-23/index.html",
            "published": "N/A",
            "source": "CNN"
        },
        {
            "title": "Video shows moment of deadly explosion at cafe in Russia",
            "link": "https://www.cnn.com/videos/world/2023/04/02/russian-military-blogger-vladlen-tatarsky-killed-cafe-explosion-chance-vpx.cnn",
            "published": "Tue, 04 Apr 2023 01:08:44 GMT",
            "source": "CNN"
        },
        {
            "title": "Wall Street Journal reporter Evan Gershkovich appeals against arrest, Russian state media says",
            "link": "https://www.cnn.com/collections/intl-ukraine-030423/",
            "published": "Mon, 03 Apr 2023 13:58:58 GMT",
            "source": "CNN"
        },
        {
            "title": "Suspected Chinese spy balloon was able to transmit information back to Beijing",
            "link": "https://www.cnn.com/2023/04/03/politics/chinese-spy-balloon/index.html",
            "published": "Mon, 03 Apr 2023 13:38:22 GMT",
            "source": "CNN"
        },
        {
            "title": "Beijing promised to 'fight back' over Taiwan leader's US visit. But this time it has more to lose",
            "link": "https://www.cnn.com/2023/04/04/asia/tsai-ing-wen-taiwan-mccarthy-meeting-analysis-intl-hnk/index.html",
            "published": "Tue, 04 Apr 2023 07:49:53 GMT",
            "source": "CNN"
        },
        {
            "title": "'Scary, cold, hungry and lonely': Volunteer soldier shares experience on front line",
            "link": "https://www.cnn.com/videos/world/2023/04/03/soldiers-russia-ukraine-war-david-mckenzie-pkg-ovn-intl-ldn-vpx.cnn",
            "published": "Mon, 03 Apr 2023 12:13:24 GMT",
            "source": "CNN"
        },
        {
            "title": "Saarland and Germany’s 'small reunification'",
            "link": "https://www.dw.com/en/saarland-and-germany-s-small-reunification/a-74212763?maca=en-rss-en-top-1022-rdf",
            "published": "2025-10-02T12:03:00Z",
            "source": "DW (Germany)"
        },
        {
            "title": "Germany news: Oktoberfest extension proposed after scare",
            "link": "https://www.dw.com/en/germany-news-oktoberfest-extension-proposed-after-scare/live-74214790?maca=en-rss-en-top-1022-rdf",
            "published": "2025-10-02T10:47:00Z",
            "source": "DW (Germany)"
        },
        {
            "title": "Pilot crisis looms as airlines scramble to fill cockpits worldwide",
            "link": "https://www.dw.com/en/pilot-crisis-looms-as-airlines-scramble-to-fill-cockpits-worldwide/a-74195149?maca=en-rss-en-top-1022-rdf",
            "published": "2025-10-02T10:07:00Z",
            "source": "DW (Germany)"
        },
        {
            "title": "Manchester: 2 killed in synagogue car, knife attack",
            "link": "https://www.dw.com/en/manchester-2-killed-in-synagogue-car-knife-attack/a-74214707?maca=en-rss-en-top-1022-rdf",
            "published": "2025-10-02T09:58:00Z",
            "source": "DW (Germany)"
        },
        {
            "title": "Czechia election: The specter of populism returns",
            "link": "https://www.dw.com/en/czechia-election-the-specter-of-populism-returns/a-74213035?maca=en-rss-en-top-1022-rdf",
            "published": "2025-10-02T09:38:00Z",
            "source": "DW (Germany)"
        },
        {
            "title": "Ukraine updates: Zelenskyy, Merz attend Denmark summit",
            "link": "https://www.dw.com/en/ukraine-updates-zelenskyy-merz-attend-denmark-summit/live-74213231?maca=en-rss-en-top-1022-rdf",
            "published": "2025-10-02T09:36:00Z",
            "source": "DW (Germany)"
        },
        {
            "title": "Indonesia school collapse: 'No signs of life' detected",
            "link": "https://www.dw.com/en/indonesia-school-collapse-no-signs-of-life-detected/a-74213060?maca=en-rss-en-top-1022-rdf",
            "published": "2025-10-02T09:24:00Z",
            "source": "DW (Germany)"
        },
        {
            "title": "Berlin to crack down on a beloved giveaway tradition",
            "link": "https://www.dw.com/en/berlin-to-crack-down-on-a-beloved-giveaway-tradition/a-74201577?maca=en-rss-en-top-1022-rdf",
            "published": "2025-10-02T09:05:00Z",
            "source": "DW (Germany)"
        },
        {
            "title": "Middle East: Israel says will deport aid flotilla activists",
            "link": "https://www.dw.com/en/middle-east-israel-says-will-deport-aid-flotilla-activists/live-74212782?maca=en-rss-en-top-1022-rdf",
            "published": "2025-10-02T08:31:00Z",
            "source": "DW (Germany)"
        },
        {
            "title": "How Germany plans to fix its drone problem",
            "link": "https://www.dw.com/en/how-germany-plans-to-fix-its-drone-problem/a-74212788?maca=en-rss-en-top-1022-rdf",
            "published": "2025-10-02T08:25:00Z",
            "source": "DW (Germany)"
        }
    ]
}