{
    "updated_at": "2025-06-28T12:23:02.205711+00:00",
    "news": [
        {
            "title": "Iran holds state funeral for military leaders killed in Israel conflict",
            "link": "https://www.bbc.com/news/articles/cvg978nkwxro",
            "published": "Sat, 28 Jun 2025 12:22:23 GMT",
            "source": "BBC"
        },
        {
            "title": "Supreme Court ruling expands Trump's power - and he intends to use it",
            "link": "https://www.bbc.com/news/articles/cj9velv7z4no",
            "published": "Fri, 27 Jun 2025 16:50:48 GMT",
            "source": "BBC"
        },
        {
            "title": "Trump says he is cutting off trade talks with Canada",
            "link": "https://www.bbc.com/news/articles/ckg629n7wzvo",
            "published": "Fri, 27 Jun 2025 20:19:38 GMT",
            "source": "BBC"
        },
        {
            "title": "Southern Europe swelters as heatwave spreads",
            "link": "https://www.bbc.com/news/articles/c5y74nv1zqpo",
            "published": "Sat, 28 Jun 2025 11:29:10 GMT",
            "source": "BBC"
        },
        {
            "title": "In pictures: Celebrities descend on Venice for Jeff Bezos and Lauren Sanchez's wedding",
            "link": "https://www.bbc.com/news/articles/cdx5g4vjz07o",
            "published": "Sat, 28 Jun 2025 08:35:05 GMT",
            "source": "BBC"
        },
        {
            "title": "Hungary Pride to go ahead, defying Orban threat of 'legal consequences'",
            "link": "https://www.bbc.com/news/articles/c23g02dl1z8o",
            "published": "Sat, 28 Jun 2025 05:45:12 GMT",
            "source": "BBC"
        },
        {
            "title": "GHF boss defends Gaza aid operation after hundreds of Palestinians killed near sites",
            "link": "https://www.bbc.com/news/articles/c20rz63g1zko",
            "published": "Fri, 27 Jun 2025 21:29:43 GMT",
            "source": "BBC"
        },
        {
            "title": "DR Congo and Rwanda sign long-awaited peace deal in Washington",
            "link": "https://www.bbc.com/news/articles/c1e0ggw7d43o",
            "published": "Fri, 27 Jun 2025 20:57:20 GMT",
            "source": "BBC"
        },
        {
            "title": "A 'fake trial': Sean 'Diddy' Combs' lawyers make final arguments to jurors",
            "link": "https://www.bbc.com/news/articles/cddzegzmqz6o",
            "published": "Fri, 27 Jun 2025 21:51:03 GMT",
            "source": "BBC"
        },
        {
            "title": "Son of Norway's crown princess suspected of rape, police say",
            "link": "https://www.bbc.com/news/articles/cyvjqn2dg3eo",
            "published": "Fri, 27 Jun 2025 17:06:51 GMT",
            "source": "BBC"
        },
        {
            "title": "Trump pleads not guilty to 34 felony counts",
            "link": "https://edition.cnn.com/webview/politics/live-news/trump-indictment-stormy-daniels-news-04-03-23/index.html",
            "published": "N/A",
            "source": "CNN"
        },
        {
            "title": "Haberman reveals why Trump attacked judge and his family in speech",
            "link": "https://www.cnn.com/videos/politics/2023/04/05/maggie-haberman-donald-trump-speech-indictment-reaction-sot-cnntm-vpx.cnn",
            "published": "Wed, 05 Apr 2023 13:30:09 GMT",
            "source": "CNN"
        },
        {
            "title": "What to know about the Trump indictment on the eve of his court appearance",
            "link": "https://www.cnn.com/collections/intl-trump-040223/",
            "published": "Wed, 05 Apr 2023 22:50:06 GMT",
            "source": "CNN"
        },
        {
            "title": "READ: Trump indictment related to hush money payment",
            "link": "https://cnn.it/411KYN7",
            "published": "N/A",
            "source": "CNN"
        },
        {
            "title": "Russian authorities detain suspect over St. Petersburg cafe blast",
            "link": "https://edition.cnn.com/webview/europe/live-news/russia-ukraine-war-news-04-03-23/index.html",
            "published": "N/A",
            "source": "CNN"
        },
        {
            "title": "Video shows moment of deadly explosion at cafe in Russia",
            "link": "https://www.cnn.com/videos/world/2023/04/02/russian-military-blogger-vladlen-tatarsky-killed-cafe-explosion-chance-vpx.cnn",
            "published": "Tue, 04 Apr 2023 01:08:44 GMT",
            "source": "CNN"
        },
        {
            "title": "Wall Street Journal reporter Evan Gershkovich appeals against arrest, Russian state media says",
            "link": "https://www.cnn.com/collections/intl-ukraine-030423/",
            "published": "Mon, 03 Apr 2023 13:58:58 GMT",
            "source": "CNN"
        },
        {
            "title": "Suspected Chinese spy balloon was able to transmit information back to Beijing",
            "link": "https://www.cnn.com/2023/04/03/politics/chinese-spy-balloon/index.html",
            "published": "Mon, 03 Apr 2023 13:38:22 GMT",
            "source": "CNN"
        },
        {
            "title": "Beijing promised to 'fight back' over Taiwan leader's US visit. But this time it has more to lose",
            "link": "https://www.cnn.com/2023/04/04/asia/tsai-ing-wen-taiwan-mccarthy-meeting-analysis-intl-hnk/index.html",
            "published": "Tue, 04 Apr 2023 07:49:53 GMT",
            "source": "CNN"
        },
        {
            "title": "'Scary, cold, hungry and lonely': Volunteer soldier shares experience on front line",
            "link": "https://www.cnn.com/videos/world/2023/04/03/soldiers-russia-ukraine-war-david-mckenzie-pkg-ovn-intl-ldn-vpx.cnn",
            "published": "Mon, 03 Apr 2023 12:13:24 GMT",
            "source": "CNN"
        },
        {
            "title": "Are designer handbags linked to illegal deforestation?",
            "link": "https://www.dw.com/en/are-designer-handbags-linked-to-illegal-deforestation/a-73044312?maca=en-rss-en-top-1022-rdf",
            "published": "2025-06-28T11:00:00Z",
            "source": "DW (Germany)"
        },
        {
            "title": "Pakistan: At least 16 soldiers killed in a suicide attack",
            "link": "https://www.dw.com/en/pakistan-at-least-16-soldiers-killed-in-a-suicide-attack/a-73076472?maca=en-rss-en-top-1022-rdf",
            "published": "2025-06-28T09:12:00Z",
            "source": "DW (Germany)"
        },
        {
            "title": "Are interceptor drones Ukraine's best option against Russia?",
            "link": "https://www.dw.com/en/are-interceptor-drones-ukraine-s-best-option-against-russia/a-73050243?maca=en-rss-en-top-1022-rdf",
            "published": "2025-06-28T08:52:00Z",
            "source": "DW (Germany)"
        },
        {
            "title": "Germany updates: Social Democrats bid farewell to Scholz",
            "link": "https://www.dw.com/en/germany-updates-social-democrats-bid-farewell-to-scholz/live-73075189?maca=en-rss-en-top-1022-rdf",
            "published": "2025-06-28T08:43:00Z",
            "source": "DW (Germany)"
        },
        {
            "title": "Middle East: Killed Iranian generals honored in Tehran",
            "link": "https://www.dw.com/en/middle-east-killed-iranian-generals-honored-in-tehran/live-73074840?maca=en-rss-en-top-1022-rdf",
            "published": "2025-06-28T08:17:00Z",
            "source": "DW (Germany)"
        },
        {
            "title": "Big attendance expected at Budapest Pride despite police ban",
            "link": "https://www.dw.com/en/big-attendance-expected-at-budapest-pride-despite-police-ban/a-73074461?maca=en-rss-en-top-1022-rdf",
            "published": "2025-06-28T06:58:00Z",
            "source": "DW (Germany)"
        },
        {
            "title": "Pakistan: Flash floods kill 11 amid heavy rain warning",
            "link": "https://www.dw.com/en/pakistan-flash-floods-kill-11-amid-heavy-rain-warning/a-73074485?maca=en-rss-en-top-1022-rdf",
            "published": "2025-06-28T06:48:00Z",
            "source": "DW (Germany)"
        },
        {
            "title": "German government shows cracks over nuclear energy",
            "link": "https://www.dw.com/en/german-government-shows-cracks-over-nuclear-energy/a-73067507?maca=en-rss-en-top-1022-rdf",
            "published": "2025-06-28T06:12:00Z",
            "source": "DW (Germany)"
        },
        {
            "title": "Son of Norway princess charged with rape and sexual assault",
            "link": "https://www.dw.com/en/son-of-norway-princess-charged-with-rape-and-sexual-assault/a-73074220?maca=en-rss-en-top-1022-rdf",
            "published": "2025-06-28T04:48:00Z",
            "source": "DW (Germany)"
        },
        {
            "title": "Gaza: Aid plan should not be 'death sentence,' UN chief says",
            "link": "https://www.dw.com/en/gaza-aid-plan-should-not-be-death-sentence-un-chief-says/a-73074000?maca=en-rss-en-top-1022-rdf",
            "published": "2025-06-28T01:24:00Z",
            "source": "DW (Germany)"
        }
    ]
}