{
    "updated_at": "2025-10-07T12:25:50.433020+00:00",
    "news": [
        {
            "title": "Jeremy Bowen: Two years on, will Israel and Hamas seize the chance to end the war?",
            "link": "https://www.bbc.com/news/articles/cvgqyj268ljo?at_medium=RSS&at_campaign=rss",
            "published": "Tue, 07 Oct 2025 08:32:25 GMT",
            "source": "BBC"
        },
        {
            "title": "Mother of Israeli hostage says she still doesn't know if he's alive or dead",
            "link": "https://www.bbc.com/news/articles/c7840n4nwx8o?at_medium=RSS&at_campaign=rss",
            "published": "Tue, 07 Oct 2025 02:32:36 GMT",
            "source": "BBC"
        },
        {
            "title": "Trump says chance of Gaza peace deal 'really good' as talks to continue in Egypt",
            "link": "https://www.bbc.com/news/articles/c708l7vgwywo?at_medium=RSS&at_campaign=rss",
            "published": "Tue, 07 Oct 2025 02:07:21 GMT",
            "source": "BBC"
        },
        {
            "title": "Albanian judge shot dead in court by man on trial",
            "link": "https://www.bbc.com/news/articles/cx25zvy78ldo?at_medium=RSS&at_campaign=rss",
            "published": "Tue, 07 Oct 2025 09:35:19 GMT",
            "source": "BBC"
        },
        {
            "title": "Macron should call early presidential vote, his first PM says",
            "link": "https://www.bbc.com/news/articles/cn0rjn3l8w2o?at_medium=RSS&at_campaign=rss",
            "published": "Tue, 07 Oct 2025 09:27:35 GMT",
            "source": "BBC"
        },
        {
            "title": "Third person dies from methanol poisoning in Brazil",
            "link": "https://www.bbc.com/news/articles/c5yvwr8p12go?at_medium=RSS&at_campaign=rss",
            "published": "Tue, 07 Oct 2025 11:51:03 GMT",
            "source": "BBC"
        },
        {
            "title": "Fifa accuses Malaysia of faking foreign-born players' eligibility",
            "link": "https://www.bbc.com/news/articles/cqxzv75dp4go?at_medium=RSS&at_campaign=rss",
            "published": "Tue, 07 Oct 2025 09:50:04 GMT",
            "source": "BBC"
        },
        {
            "title": "US shutdown to continue after funding measures fail again in Senate",
            "link": "https://www.bbc.com/news/articles/cr5q0zzdepeo?at_medium=RSS&at_campaign=rss",
            "published": "Mon, 06 Oct 2025 23:07:18 GMT",
            "source": "BBC"
        },
        {
            "title": "Carney to meet Trump in search of 'best deal for Canada'",
            "link": "https://www.bbc.com/news/articles/cn76424yd2mo?at_medium=RSS&at_campaign=rss",
            "published": "Tue, 07 Oct 2025 08:09:23 GMT",
            "source": "BBC"
        },
        {
            "title": "Army general named as Madagascar PM to quell Gen Z protests",
            "link": "https://www.bbc.com/news/articles/c20z7e2pyw5o?at_medium=RSS&at_campaign=rss",
            "published": "Tue, 07 Oct 2025 11:32:50 GMT",
            "source": "BBC"
        },
        {
            "title": "Trump pleads not guilty to 34 felony counts",
            "link": "https://edition.cnn.com/webview/politics/live-news/trump-indictment-stormy-daniels-news-04-03-23/index.html",
            "published": "N/A",
            "source": "CNN"
        },
        {
            "title": "Haberman reveals why Trump attacked judge and his family in speech",
            "link": "https://www.cnn.com/videos/politics/2023/04/05/maggie-haberman-donald-trump-speech-indictment-reaction-sot-cnntm-vpx.cnn",
            "published": "Wed, 05 Apr 2023 13:30:09 GMT",
            "source": "CNN"
        },
        {
            "title": "What to know about the Trump indictment on the eve of his court appearance",
            "link": "https://www.cnn.com/collections/intl-trump-040223/",
            "published": "Wed, 05 Apr 2023 22:50:06 GMT",
            "source": "CNN"
        },
        {
            "title": "READ: Trump indictment related to hush money payment",
            "link": "https://cnn.it/411KYN7",
            "published": "N/A",
            "source": "CNN"
        },
        {
            "title": "Russian authorities detain suspect over St. Petersburg cafe blast",
            "link": "https://edition.cnn.com/webview/europe/live-news/russia-ukraine-war-news-04-03-23/index.html",
            "published": "N/A",
            "source": "CNN"
        },
        {
            "title": "Video shows moment of deadly explosion at cafe in Russia",
            "link": "https://www.cnn.com/videos/world/2023/04/02/russian-military-blogger-vladlen-tatarsky-killed-cafe-explosion-chance-vpx.cnn",
            "published": "Tue, 04 Apr 2023 01:08:44 GMT",
            "source": "CNN"
        },
        {
            "title": "Wall Street Journal reporter Evan Gershkovich appeals against arrest, Russian state media says",
            "link": "https://www.cnn.com/collections/intl-ukraine-030423/",
            "published": "Mon, 03 Apr 2023 13:58:58 GMT",
            "source": "CNN"
        },
        {
            "title": "Suspected Chinese spy balloon was able to transmit information back to Beijing",
            "link": "https://www.cnn.com/2023/04/03/politics/chinese-spy-balloon/index.html",
            "published": "Mon, 03 Apr 2023 13:38:22 GMT",
            "source": "CNN"
        },
        {
            "title": "Beijing promised to 'fight back' over Taiwan leader's US visit. But this time it has more to lose",
            "link": "https://www.cnn.com/2023/04/04/asia/tsai-ing-wen-taiwan-mccarthy-meeting-analysis-intl-hnk/index.html",
            "published": "Tue, 04 Apr 2023 07:49:53 GMT",
            "source": "CNN"
        },
        {
            "title": "'Scary, cold, hungry and lonely': Volunteer soldier shares experience on front line",
            "link": "https://www.cnn.com/videos/world/2023/04/03/soldiers-russia-ukraine-war-david-mckenzie-pkg-ovn-intl-ldn-vpx.cnn",
            "published": "Mon, 03 Apr 2023 12:13:24 GMT",
            "source": "CNN"
        },
        {
            "title": "Is Vietnam turning against LGBTQ+ rights?",
            "link": "https://www.dw.com/en/is-vietnam-turning-against-lgbtq-rights/a-74262807?maca=en-rss-en-top-1022-rdf",
            "published": "2025-10-07T12:21:00Z",
            "source": "DW (Germany)"
        },
        {
            "title": "Ukraine updates: Kyiv seeks G7 natural gas imports",
            "link": "https://www.dw.com/en/ukraine-updates-kyiv-seeks-g7-natural-gas-imports/live-74262818?maca=en-rss-en-top-1022-rdf",
            "published": "2025-10-07T11:52:00Z",
            "source": "DW (Germany)"
        },
        {
            "title": "German Chancellor Merz suggests a return to conscription",
            "link": "https://www.dw.com/en/german-chancellor-merz-suggests-a-return-to-conscription/a-73785847?maca=en-rss-en-top-1022-rdf",
            "published": "2025-10-07T11:46:00Z",
            "source": "DW (Germany)"
        },
        {
            "title": "Lee Miller: From surrealist muse to war photographer",
            "link": "https://www.dw.com/en/lee-miller-from-surrealist-muse-to-war-photographer/a-65846772?maca=en-rss-en-top-1022-rdf",
            "published": "2025-10-06T12:20:00Z",
            "source": "DW (Germany)"
        },
        {
            "title": "Could France's political turmoil spark eurozone debt crisis?",
            "link": "https://www.dw.com/en/could-france-s-political-turmoil-spark-eurozone-debt-crisis/a-73886339?maca=en-rss-en-top-1022-rdf",
            "published": "2025-10-07T11:43:00Z",
            "source": "DW (Germany)"
        },
        {
            "title": "Germany news: October 7 commemorations held across country",
            "link": "https://www.dw.com/en/germany-news-october-7-commemorations-held-across-country/live-74258849?maca=en-rss-en-top-1022-rdf",
            "published": "2025-10-07T11:03:00Z",
            "source": "DW (Germany)"
        },
        {
            "title": "Nobel Prize in physics goes to US-based trio for discoveries in quantum mechanics",
            "link": "https://www.dw.com/en/nobel-prize-in-physics-goes-to-us-based-trio-for-discoveries-in-quantum-mechanics/a-74260795?maca=en-rss-en-top-1022-rdf",
            "published": "2025-10-07T09:53:00Z",
            "source": "DW (Germany)"
        },
        {
            "title": "Exhibition recalls Hamas attack on the Nova Music Festival",
            "link": "https://www.dw.com/en/exhibition-recalls-hamas-attack-on-the-nova-music-festival/a-74259993?maca=en-rss-en-top-1022-rdf",
            "published": "2025-10-07T08:47:00Z",
            "source": "DW (Germany)"
        },
        {
            "title": "Election in Cameroon: Will the 'frustrated' youth vote?",
            "link": "https://www.dw.com/en/election-in-cameroon-will-the-frustrated-youth-vote/a-74247248?maca=en-rss-en-top-1022-rdf",
            "published": "2025-10-07T08:35:00Z",
            "source": "DW (Germany)"
        },
        {
            "title": "UNESCO board nominates Egyptian ex-minister for director",
            "link": "https://www.dw.com/en/unesco-board-nominates-egyptian-ex-minister-for-director/a-74259365?maca=en-rss-en-top-1022-rdf",
            "published": "2025-10-07T08:22:00Z",
            "source": "DW (Germany)"
        }
    ]
}